bibleg/__init__.py
bibleg-0.2.0.dist-info/METADATA
bibleg-0.2.0.dist-info/WHEEL
bibleg-0.2.0.dist-info/top_level.txt
bibleg-0.2.0.dist-info/RECORD
