Metadata-Version: 2.4
Name: bibleg
Version: 0.2.0
Summary: Unofficial Bible API
Author-email: Jon Craton <jon@joncraton.com>
License-Expression: MIT
Project-URL: Homepage, https://github.com/jncraton/bibleg
Project-URL: Issues, https://github.com/jncraton/bibleg
Classifier: Programming Language :: Python :: 3
Classifier: Operating System :: OS Independent
Requires-Python: >=3.9
